AHItoDICOMInterface/AHIClientFactory.py
AHItoDICOMInterface/AHIDataDICOMizer.py
AHItoDICOMInterface/AHIFrameFetcher.py
AHItoDICOMInterface/AHItoDICOM.py
AHItoDICOMInterface/__init__.py
AHItoDICOMInterface-0.1.3.4.dist-info/LICENSE
AHItoDICOMInterface-0.1.3.4.dist-info/METADATA
AHItoDICOMInterface-0.1.3.4.dist-info/NOTICE
AHItoDICOMInterface-0.1.3.4.dist-info/WHEEL
AHItoDICOMInterface-0.1.3.4.dist-info/top_level.txt
AHItoDICOMInterface-0.1.3.4.dist-info/RECORD
