Metadata-Version: 2.1
Name: AHItoDICOMInterface
Version: 0.1.3.4
Summary: A package to simply export DICOM data from AWS HealthImaging in your application memory or the file system.
Home-page: https://github.com/aws-samples/healthlake-imaging-to-dicom-python-module
Author: JP Leger
Author-email: jpleger@amazon.com
License: MIT-0
Classifier: Development Status :: 4 - Beta
Classifier: Intended Audience :: Science/Research
Classifier: License :: OSI Approved :: MIT No Attribution License (MIT-0)
Classifier: Operating System :: POSIX :: Linux
Classifier: Operating System :: Microsoft :: Windows
Classifier: Programming Language :: Python :: 3.10
Classifier: Programming Language :: Python :: 3.11
License-File: LICENSE
License-File: NOTICE
Requires-Dist: boto3
Requires-Dist: botocore
Requires-Dist: pydicom
Requires-Dist: pylibjpeg-openjpeg >=1.3.0
Requires-Dist: numpy
Requires-Dist: pillow
